zinnia_blogger/__init__.py
zinnia_blogger/management/__init__.py
zinnia_blogger/management/commands/blogger2zinnia.py
zinnia_blogger/management/commands/__init__.py
feed2zinnia-1.0.dist-info/metadata.json
feed2zinnia-1.0.dist-info/METADATA
feed2zinnia-1.0.dist-info/RECORD
feed2zinnia-1.0.dist-info/WHEEL
feed2zinnia-1.0.dist-info/DESCRIPTION.rst
feed2zinnia-1.0.dist-info/top_level.txt
zinnia_feed/__init__.py
zinnia_feed/management/__init__.py
zinnia_feed/management/commands/__init__.py
zinnia_feed/management/commands/feed2zinnia.py
